[
  {
    "Site_ID":61401973,
    "Fuel_ID":2,
    "TransactionDate":"2026-06-20T09:05:07+10:00",
    "Price":1.675,
    "Name":"United Gordonvale",
    "Address":"68 Riverstone Road",
    "Postcode":"4865",
    "Fuel_Name":"Unleaded"
  },
  {
    "Site_ID":61401991,
    "Fuel_ID":2,
    "TransactionDate":"2026-06-18T18:54:54+10:00",
    "Price":1.705,
    "Name":"BP Edmonton",
    "Address":"3\/167 Bruce Hwy",
    "Postcode":"4869",
    "Fuel_Name":"Unleaded"
  },
  {
    "Site_ID":61402009,
    "Fuel_ID":2,
    "TransactionDate":"2026-06-18T09:07:32+10:00",
    "Price":1.719,
    "Name":"Ampol Mossman",
    "Address":"67 Alchera",
    "Postcode":"4873",
    "Fuel_Name":"Unleaded"
  },
  {
    "Site_ID":61402015,
    "Fuel_ID":2,
    "TransactionDate":"2026-06-18T10:37:28+10:00",
    "Price":1.699,
    "Name":"Billabong Service Centre",
    "Address":"Captain Cook Hwy",
    "Postcode":"4879",
    "Fuel_Name":"Unleaded"
  },
  {
    "Site_ID":61402067,
    "Fuel_ID":2,
    "TransactionDate":"2026-06-19T16:05:52+10:00",
    "Price":1.615,
    "Name":"Caltex Woree",
    "Address":"590 Mulgrave Rd",
    "Postcode":"4868",
    "Fuel_Name":"Unleaded"
  },
  {
    "Site_ID":61402073,
    "Fuel_ID":2,
    "TransactionDate":"2026-06-19T15:32:17+10:00",
    "Price":1.649,
    "Name":"Ampol Foodary Cairns Sheridan St",
    "Address":"131 Sheridan St",
    "Postcode":"4870",
    "Fuel_Name":"Unleaded"
  },
  {
    "Site_ID":61402272,
    "Fuel_ID":2,
    "TransactionDate":"2026-06-20T09:02:41+10:00",
    "Price":1.675,
    "Name":"Mobil Brinsmead",
    "Address":"101-115 Brinsmead Road",
    "Postcode":"4870",
    "Fuel_Name":"Unleaded"
  },
  {
    "Site_ID":61402393,
    "Fuel_ID":2,
    "TransactionDate":"2026-06-19T09:28:43+10:00",
    "Price":1.699,
    "Name":"Caltex Stratford",
    "Address":"45 Arnold St",
    "Postcode":"4870",
    "Fuel_Name":"Unleaded"
  },
  {
    "Site_ID":61402394,
    "Fuel_ID":2,
    "TransactionDate":"2026-06-18T12:19:17+10:00",
    "Price":1.699,
    "Name":"Caltex Bentley Park",
    "Address":"28 Supply Rd",
    "Postcode":"4869",
    "Fuel_Name":"Unleaded"
  },
  {
    "Site_ID":61402395,
    "Fuel_ID":2,
    "TransactionDate":"2026-06-15T11:10:02+10:00",
    "Price":1.699,
    "Name":"Caltex Portsmith",
    "Address":"104 Cook St, Portsmith QLD 4870, Australia",
    "Postcode":"4870",
    "Fuel_Name":"Unleaded"
  },
  {
    "Site_ID":61402549,
    "Fuel_ID":2,
    "TransactionDate":"2026-06-17T08:47:23+10:00",
    "Price":1.61,
    "Name":"Zenna's General Store",
    "Address":"177 Howard Kennedy Dr",
    "Postcode":"4861",
    "Fuel_Name":"Unleaded"
  },
  {
    "Site_ID":61402555,
    "Fuel_ID":2,
    "TransactionDate":"2026-06-18T09:14:05+10:00",
    "Price":1.719,
    "Name":"Astron Twin Rivers",
    "Address":"68929 Bruce Highway",
    "Postcode":"4871",
    "Fuel_Name":"Unleaded"
  },
  {
    "Site_ID":61402769,
    "Fuel_ID":2,
    "TransactionDate":"2026-06-17T10:00:10+10:00",
    "Price":1.695,
    "Name":"United Koah",
    "Address":"2 Koah Rd",
    "Postcode":"4872",
    "Fuel_Name":"Unleaded"
  },
  {
    "Site_ID":61402795,
    "Fuel_ID":2,
    "TransactionDate":"2026-06-18T10:25:09+10:00",
    "Price":1.679,
    "Name":"BP Mossman",
    "Address":"68 Pringle St",
    "Postcode":"4873",
    "Fuel_Name":"Unleaded"
  },
  {
    "Site_ID":61402827,
    "Fuel_ID":2,
    "TransactionDate":"2026-06-19T16:05:07+10:00",
    "Price":1.635,
    "Name":"United Cairns North",
    "Address":"238 Sheridan Street",
    "Postcode":"4870",
    "Fuel_Name":"Unleaded"
  },
  {
    "Site_ID":61402828,
    "Fuel_ID":2,
    "TransactionDate":"2026-06-10T10:20:08+10:00",
    "Price":1.615,
    "Name":"United Woree",
    "Address":"6 Southgate Close",
    "Postcode":"4868",
    "Fuel_Name":"Unleaded"
  },
  {
    "Site_ID":61402869,
    "Fuel_ID":2,
    "TransactionDate":"2026-06-20T09:15:07+10:00",
    "Price":1.675,
    "Name":"United Gordonvale Cairns Road",
    "Address":"105-115 Cairns Road",
    "Postcode":"4865",
    "Fuel_Name":"Unleaded"
  },
  {
    "Site_ID":61402891,
    "Fuel_ID":2,
    "TransactionDate":"2026-06-11T16:30:34+10:00",
    "Price":1.699,
    "Name":"Shell Reddy Express Edmonton",
    "Address":"9-11 Walker Rd (Cnr Hambledon Dr)",
    "Postcode":"4869",
    "Fuel_Name":"Unleaded"
  },
  {
    "Site_ID":61451561,
    "Fuel_ID":2,
    "TransactionDate":"2026-06-20T08:38:42+10:00",
    "Price":1.675,
    "Name":"Mobil Edmonton",
    "Address":"75 Bruce Hwy",
    "Postcode":"4869",
    "Fuel_Name":"Unleaded"
  },
  {
    "Site_ID":61451566,
    "Fuel_ID":2,
    "TransactionDate":"2026-06-19T10:45:25+10:00",
    "Price":1.679,
    "Name":"Shell Reddy Express Reservoir (Qld)",
    "Address":"58 Pease St",
    "Postcode":"4870",
    "Fuel_Name":"Unleaded"
  },
  {
    "Site_ID":61451567,
    "Fuel_ID":2,
    "TransactionDate":"2026-06-19T10:30:30+10:00",
    "Price":1.659,
    "Name":"Shell Reddy Express Cairns Sheridan St",
    "Address":"291-293 Sheridan St",
    "Postcode":"4870",
    "Fuel_Name":"Unleaded"
  },
  {
    "Site_ID":61451572,
    "Fuel_ID":2,
    "TransactionDate":"2026-06-17T09:30:34+10:00",
    "Price":1.699,
    "Name":"Shell Reddy Express Smithfield (Qld)",
    "Address":"Lot 1 Captain Cook Hwy",
    "Postcode":"4878",
    "Fuel_Name":"Unleaded"
  },
  {
    "Site_ID":61451666,
    "Fuel_ID":2,
    "TransactionDate":"2026-06-19T15:30:32+10:00",
    "Price":1.615,
    "Name":"Liberty Woree",
    "Address":"540 Mulgrave Road",
    "Postcode":"4868",
    "Fuel_Name":"Unleaded"
  },
  {
    "Site_ID":61451722,
    "Fuel_ID":2,
    "TransactionDate":"2026-06-18T08:07:49+10:00",
    "Price":1.695,
    "Name":"Mobil Yorkey's Knob",
    "Address":"233 Yorkeys Knob Road",
    "Postcode":"4878",
    "Fuel_Name":"Unleaded"
  },
  {
    "Site_ID":61451728,
    "Fuel_ID":2,
    "TransactionDate":"2026-06-18T09:26:40+10:00",
    "Price":1.699,
    "Name":"Shell Cairns",
    "Address":"8 Kenny St, Portsmith QLD 4870, Australia",
    "Postcode":"4870",
    "Fuel_Name":"Unleaded"
  },
  {
    "Site_ID":61451734,
    "Fuel_ID":2,
    "TransactionDate":"2026-06-19T10:35:24+10:00",
    "Price":1.719,
    "Name":"Shell Reddy Express Port Douglas",
    "Address":"10 Captain Cook Hwy",
    "Postcode":"4877",
    "Fuel_Name":"Unleaded"
  },
  {
    "Site_ID":61470034,
    "Fuel_ID":2,
    "TransactionDate":"2026-06-06T07:32:42+10:00",
    "Price":1.695,
    "Name":"Mobil Gordonvale",
    "Address":"67 George St",
    "Postcode":"4865",
    "Fuel_Name":"Unleaded"
  },
  {
    "Site_ID":61470086,
    "Fuel_ID":2,
    "TransactionDate":"2026-06-04T12:55:53+10:00",
    "Price":1.695,
    "Name":"Mobil on Spence",
    "Address":"142A-146 Spence Street",
    "Postcode":"4870",
    "Fuel_Name":"Unleaded"
  },
  {
    "Site_ID":61470115,
    "Fuel_ID":2,
    "TransactionDate":"2026-06-09T13:08:39+10:00",
    "Price":1.889,
    "Name":"Thorpe Earthmoving",
    "Address":"14 Perkins Street",
    "Postcode":"4887",
    "Fuel_Name":"Unleaded"
  },
  {
    "Site_ID":61470145,
    "Fuel_ID":2,
    "TransactionDate":"2026-06-19T06:14:32+10:00",
    "Price":1.709,
    "Name":"Ampol Port Douglas",
    "Address":"13 Warner St",
    "Postcode":"4871",
    "Fuel_Name":"Unleaded"
  },
  {
    "Site_ID":61470301,
    "Fuel_ID":2,
    "TransactionDate":"2026-06-16T07:55:03+10:00",
    "Price":1.709,
    "Name":"NightOwl BP Clifton Beach",
    "Address":"55-57 Endeavour Road",
    "Postcode":"4879",
    "Fuel_Name":"Unleaded"
  },
  {
    "Site_ID":61470573,
    "Fuel_ID":2,
    "TransactionDate":"2026-06-20T10:10:17+10:00",
    "Price":1.649,
    "Name":"BP Earlville",
    "Address":"395 Mulgrave Rd & Mccoombe Rd",
    "Postcode":"4870",
    "Fuel_Name":"Unleaded"
  },
  {
    "Site_ID":61470699,
    "Fuel_ID":2,
    "TransactionDate":"2026-06-19T10:18:04+10:00",
    "Price":1.695,
    "Name":"BP Kuranda",
    "Address":"3 Rob Veivers Drive",
    "Postcode":"4881",
    "Fuel_Name":"Unleaded"
  },
  {
    "Site_ID":61477011,
    "Fuel_ID":2,
    "TransactionDate":"2026-06-19T15:35:31+10:00",
    "Price":1.635,
    "Name":"Liberty Manoora",
    "Address":"31-35 Reservoir Rd",
    "Postcode":"4870",
    "Fuel_Name":"Unleaded"
  },
  {
    "Site_ID":61477020,
    "Fuel_ID":2,
    "TransactionDate":"2026-06-19T15:32:17+10:00",
    "Price":1.649,
    "Name":"Ampol Foodary Manunda",
    "Address":"1 Hoare St & Gatton Rd",
    "Postcode":"4870",
    "Fuel_Name":"Unleaded"
  },
  {
    "Site_ID":61477041,
    "Fuel_ID":2,
    "TransactionDate":"2026-06-19T18:40:23+10:00",
    "Price":1.629,
    "Name":"OOM Energy Cairns Central",
    "Address":"Cnr Martyn & Florence St",
    "Postcode":"4870",
    "Fuel_Name":"Unleaded"
  },
  {
    "Site_ID":61477062,
    "Fuel_ID":2,
    "TransactionDate":"2026-06-20T10:10:17+10:00",
    "Price":1.699,
    "Name":"BP Smithfield Cairns",
    "Address":"Captain Cook Hwy",
    "Postcode":"4878",
    "Fuel_Name":"Unleaded"
  },
  {
    "Site_ID":61477095,
    "Fuel_ID":2,
    "TransactionDate":"2026-06-17T09:35:23+10:00",
    "Price":1.699,
    "Name":"Shell Reddy Express Redlynch",
    "Address":"1A Chelsea Lane",
    "Postcode":"4878",
    "Fuel_Name":"Unleaded"
  },
  {
    "Site_ID":61477106,
    "Fuel_ID":2,
    "TransactionDate":"2026-06-18T09:26:44+10:00",
    "Price":1.719,
    "Name":"Marano\u2019s Fuel Wonga",
    "Address":"3 Oleander Drive",
    "Postcode":"4873",
    "Fuel_Name":"Unleaded"
  },
  {
    "Site_ID":61477674,
    "Fuel_ID":2,
    "TransactionDate":"2026-06-18T08:35:19+10:00",
    "Price":1.655,
    "Name":"Edge Hill Servo",
    "Address":"134 Collins Ave",
    "Postcode":"4870",
    "Fuel_Name":"Unleaded"
  },
  {
    "Site_ID":61477719,
    "Fuel_ID":2,
    "TransactionDate":"2026-06-19T10:30:30+10:00",
    "Price":1.649,
    "Name":"Shell Reddy Express Cairns Mulgrave Rd",
    "Address":"87 Mulgrave Rd",
    "Postcode":"4870",
    "Fuel_Name":"Unleaded"
  },
  {
    "Site_ID":61477726,
    "Fuel_ID":2,
    "TransactionDate":"2026-06-05T08:12:01+10:00",
    "Price":1.699,
    "Name":"White Rock General Store",
    "Address":"150 Progress Road",
    "Postcode":"4868",
    "Fuel_Name":"Unleaded"
  },
  {
    "Site_ID":61477727,
    "Fuel_ID":2,
    "TransactionDate":"2026-06-18T09:07:24+10:00",
    "Price":1.655,
    "Name":"Machans Beach Store and Post Office",
    "Address":"27 Machans Street",
    "Postcode":"4878",
    "Fuel_Name":"Unleaded"
  },
  {
    "Site_ID":61477771,
    "Fuel_ID":2,
    "TransactionDate":"2026-06-15T06:50:13+10:00",
    "Price":1.729,
    "Name":"Eacham Fuels",
    "Address":"8 Pioneer Avenue",
    "Postcode":"4885",
    "Fuel_Name":"Unleaded"
  },
  {
    "Site_ID":61477804,
    "Fuel_ID":2,
    "TransactionDate":"2026-06-15T17:32:50+10:00",
    "Price":1.737,
    "Name":"Stratford Driveway Discount Fuels",
    "Address":"2-4 Rinks Close",
    "Postcode":"4870",
    "Fuel_Name":"Unleaded"
  },
  {
    "Site_ID":61477805,
    "Fuel_ID":2,
    "TransactionDate":"2026-06-19T10:08:25+10:00",
    "Price":1.695,
    "Name":"Mobil Edmonton Central",
    "Address":"59-63 Hambleton Drive",
    "Postcode":"4869",
    "Fuel_Name":"Unleaded"
  },
  {
    "Site_ID":61477814,
    "Fuel_ID":2,
    "TransactionDate":"2026-06-18T09:12:34+10:00",
    "Price":1.719,
    "Name":"Miallo Fuel Station",
    "Address":"735 Daintree Road",
    "Postcode":"4873",
    "Fuel_Name":"Unleaded"
  },
  {
    "Site_ID":61477816,
    "Fuel_ID":2,
    "TransactionDate":"2026-06-18T10:17:14+10:00",
    "Price":1.719,
    "Name":"Roadhouse Service Station",
    "Address":"129 Alchera Drive",
    "Postcode":"4873",
    "Fuel_Name":"Unleaded"
  },
  {
    "Site_ID":61477819,
    "Fuel_ID":2,
    "TransactionDate":"2026-06-18T09:17:34+10:00",
    "Price":1.719,
    "Name":"Port Douglas Service Station",
    "Address":" Port Street",
    "Postcode":"4871",
    "Fuel_Name":"Unleaded"
  },
  {
    "Site_ID":61477822,
    "Fuel_ID":2,
    "TransactionDate":"2026-06-18T09:37:47+10:00",
    "Price":1.719,
    "Name":"Raintrees Cafe and Servo",
    "Address":"2 Foxton Avenue",
    "Postcode":"4873",
    "Fuel_Name":"Unleaded"
  },
  {
    "Site_ID":61477837,
    "Fuel_ID":2,
    "TransactionDate":"2026-06-18T12:03:22+10:00",
    "Price":1.719,
    "Name":"BP Port Douglas",
    "Address":"5946 Davidson Street",
    "Postcode":"4877",
    "Fuel_Name":"Unleaded"
  },
  {
    "Site_ID":61477839,
    "Fuel_ID":2,
    "TransactionDate":"2026-06-09T13:08:39+10:00",
    "Price":1.889,
    "Name":"Wondecla Service Station",
    "Address":"1190 Longlands Gap Rd",
    "Postcode":"4887",
    "Fuel_Name":"Unleaded"
  },
  {
    "Site_ID":61477987,
    "Fuel_ID":2,
    "TransactionDate":"2026-06-20T08:15:39+10:00",
    "Price":1.645,
    "Name":"Mobil Sheridan Street",
    "Address":"237-241 Sheridan Street",
    "Postcode":"4870",
    "Fuel_Name":"Unleaded"
  },
  {
    "Site_ID":61478023,
    "Fuel_ID":2,
    "TransactionDate":"2026-06-18T09:31:47+10:00",
    "Price":1.699,
    "Name":"Marano\u2019s Fuel Edmonton",
    "Address":"69-70 Thomson Road",
    "Postcode":"4869",
    "Fuel_Name":"Unleaded"
  },
  {
    "Site_ID":61478243,
    "Fuel_ID":2,
    "TransactionDate":"2026-06-18T14:25:05+10:00",
    "Price":1.689,
    "Name":"NightOwl BP Anderson Street",
    "Address":"66-68 Anderson St",
    "Postcode":"4870",
    "Fuel_Name":"Unleaded"
  },
  {
    "Site_ID":61401973,
    "Fuel_ID":3,
    "TransactionDate":"2026-06-19T11:05:12+10:00",
    "Price":1.953,
    "Name":"United Gordonvale",
    "Address":"68 Riverstone Road",
    "Postcode":"4865",
    "Fuel_Name":"Diesel"
  },
  {
    "Site_ID":61401991,
    "Fuel_ID":3,
    "TransactionDate":"2026-06-18T18:54:54+10:00",
    "Price":1.995,
    "Name":"BP Edmonton",
    "Address":"3\/167 Bruce Hwy",
    "Postcode":"4869",
    "Fuel_Name":"Diesel"
  },
  {
    "Site_ID":61402009,
    "Fuel_ID":3,
    "TransactionDate":"2026-06-18T09:07:32+10:00",
    "Price":2.079,
    "Name":"Ampol Mossman",
    "Address":"67 Alchera",
    "Postcode":"4873",
    "Fuel_Name":"Diesel"
  },
  {
    "Site_ID":61402015,
    "Fuel_ID":3,
    "TransactionDate":"2026-06-18T10:37:28+10:00",
    "Price":1.999,
    "Name":"Billabong Service Centre",
    "Address":"Captain Cook Hwy",
    "Postcode":"4879",
    "Fuel_Name":"Diesel"
  },
  {
    "Site_ID":61402067,
    "Fuel_ID":3,
    "TransactionDate":"2026-06-19T16:05:52+10:00",
    "Price":1.895,
    "Name":"Caltex Woree",
    "Address":"590 Mulgrave Rd",
    "Postcode":"4868",
    "Fuel_Name":"Diesel"
  },
  {
    "Site_ID":61402272,
    "Fuel_ID":3,
    "TransactionDate":"2026-06-19T08:05:07+10:00",
    "Price":1.955,
    "Name":"Mobil Brinsmead",
    "Address":"101-115 Brinsmead Road",
    "Postcode":"4870",
    "Fuel_Name":"Diesel"
  },
  {
    "Site_ID":61402357,
    "Fuel_ID":3,
    "TransactionDate":"2026-06-19T17:05:52+10:00",
    "Price":1.889,
    "Name":"Ampol Cairns",
    "Address":"60 Draper Street",
    "Postcode":"4870",
    "Fuel_Name":"Diesel"
  },
  {
    "Site_ID":61402549,
    "Fuel_ID":3,
    "TransactionDate":"2026-06-17T08:47:23+10:00",
    "Price":1.89,
    "Name":"Zenna's General Store",
    "Address":"177 Howard Kennedy Dr",
    "Postcode":"4861",
    "Fuel_Name":"Diesel"
  },
  {
    "Site_ID":61402555,
    "Fuel_ID":3,
    "TransactionDate":"2026-06-18T09:14:05+10:00",
    "Price":2.099,
    "Name":"Astron Twin Rivers",
    "Address":"68929 Bruce Highway",
    "Postcode":"4871",
    "Fuel_Name":"Diesel"
  },
  {
    "Site_ID":61402769,
    "Fuel_ID":3,
    "TransactionDate":"2026-06-19T11:50:10+10:00",
    "Price":1.959,
    "Name":"United Koah",
    "Address":"2 Koah Rd",
    "Postcode":"4872",
    "Fuel_Name":"Diesel"
  },
  {
    "Site_ID":61402795,
    "Fuel_ID":3,
    "TransactionDate":"2026-06-18T10:25:09+10:00",
    "Price":2.039,
    "Name":"BP Mossman",
    "Address":"68 Pringle St",
    "Postcode":"4873",
    "Fuel_Name":"Diesel"
  },
  {
    "Site_ID":61402827,
    "Fuel_ID":3,
    "TransactionDate":"2026-06-19T16:05:07+10:00",
    "Price":1.895,
    "Name":"United Cairns North",
    "Address":"238 Sheridan Street",
    "Postcode":"4870",
    "Fuel_Name":"Diesel"
  },
  {
    "Site_ID":61402828,
    "Fuel_ID":3,
    "TransactionDate":"2026-06-19T16:05:07+10:00",
    "Price":1.895,
    "Name":"United Woree",
    "Address":"6 Southgate Close",
    "Postcode":"4868",
    "Fuel_Name":"Diesel"
  },
  {
    "Site_ID":61402869,
    "Fuel_ID":3,
    "TransactionDate":"2026-06-19T10:55:06+10:00",
    "Price":1.953,
    "Name":"United Gordonvale Cairns Road",
    "Address":"105-115 Cairns Road",
    "Postcode":"4865",
    "Fuel_Name":"Diesel"
  },
  {
    "Site_ID":61402891,
    "Fuel_ID":3,
    "TransactionDate":"2026-06-19T10:30:30+10:00",
    "Price":1.954,
    "Name":"Shell Reddy Express Edmonton",
    "Address":"9-11 Walker Rd (Cnr Hambledon Dr)",
    "Postcode":"4869",
    "Fuel_Name":"Diesel"
  },
  {
    "Site_ID":61451561,
    "Fuel_ID":3,
    "TransactionDate":"2026-06-20T08:38:42+10:00",
    "Price":1.955,
    "Name":"Mobil Edmonton",
    "Address":"75 Bruce Hwy",
    "Postcode":"4869",
    "Fuel_Name":"Diesel"
  },
  {
    "Site_ID":61451566,
    "Fuel_ID":3,
    "TransactionDate":"2026-06-19T10:45:25+10:00",
    "Price":1.999,
    "Name":"Shell Reddy Express Reservoir (Qld)",
    "Address":"58 Pease St",
    "Postcode":"4870",
    "Fuel_Name":"Diesel"
  },
  {
    "Site_ID":61451567,
    "Fuel_ID":3,
    "TransactionDate":"2026-06-19T10:30:30+10:00",
    "Price":1.994,
    "Name":"Shell Reddy Express Cairns Sheridan St",
    "Address":"291-293 Sheridan St",
    "Postcode":"4870",
    "Fuel_Name":"Diesel"
  },
  {
    "Site_ID":61451572,
    "Fuel_ID":3,
    "TransactionDate":"2026-06-19T10:20:23+10:00",
    "Price":1.959,
    "Name":"Shell Reddy Express Smithfield (Qld)",
    "Address":"Lot 1 Captain Cook Hwy",
    "Postcode":"4878",
    "Fuel_Name":"Diesel"
  },
  {
    "Site_ID":61451666,
    "Fuel_ID":3,
    "TransactionDate":"2026-06-19T15:30:38+10:00",
    "Price":1.895,
    "Name":"Liberty Woree",
    "Address":"540 Mulgrave Road",
    "Postcode":"4868",
    "Fuel_Name":"Diesel"
  },
  {
    "Site_ID":61451722,
    "Fuel_ID":3,
    "TransactionDate":"2026-06-19T07:31:05+10:00",
    "Price":1.955,
    "Name":"Mobil Yorkey's Knob",
    "Address":"233 Yorkeys Knob Road",
    "Postcode":"4878",
    "Fuel_Name":"Diesel"
  },
  {
    "Site_ID":61451728,
    "Fuel_ID":3,
    "TransactionDate":"2026-06-18T09:26:40+10:00",
    "Price":1.999,
    "Name":"Shell Cairns",
    "Address":"8 Kenny St, Portsmith QLD 4870, Australia",
    "Postcode":"4870",
    "Fuel_Name":"Diesel"
  },
  {
    "Site_ID":61451734,
    "Fuel_ID":3,
    "TransactionDate":"2026-06-19T10:35:24+10:00",
    "Price":2.074,
    "Name":"Shell Reddy Express Port Douglas",
    "Address":"10 Captain Cook Hwy",
    "Postcode":"4877",
    "Fuel_Name":"Diesel"
  },
  {
    "Site_ID":61470034,
    "Fuel_ID":3,
    "TransactionDate":"2026-06-20T09:48:22+10:00",
    "Price":1.955,
    "Name":"Mobil Gordonvale",
    "Address":"67 George St",
    "Postcode":"4865",
    "Fuel_Name":"Diesel"
  },
  {
    "Site_ID":61470086,
    "Fuel_ID":3,
    "TransactionDate":"2026-06-20T08:53:27+10:00",
    "Price":1.895,
    "Name":"Mobil on Spence",
    "Address":"142A-146 Spence Street",
    "Postcode":"4870",
    "Fuel_Name":"Diesel"
  },
  {
    "Site_ID":61470115,
    "Fuel_ID":3,
    "TransactionDate":"2026-06-09T13:08:39+10:00",
    "Price":2.219,
    "Name":"Thorpe Earthmoving",
    "Address":"14 Perkins Street",
    "Postcode":"4887",
    "Fuel_Name":"Diesel"
  },
  {
    "Site_ID":61470145,
    "Fuel_ID":3,
    "TransactionDate":"2026-06-19T06:14:32+10:00",
    "Price":2.059,
    "Name":"Ampol Port Douglas",
    "Address":"13 Warner St",
    "Postcode":"4871",
    "Fuel_Name":"Diesel"
  },
  {
    "Site_ID":61470301,
    "Fuel_ID":3,
    "TransactionDate":"2026-06-16T08:09:06+10:00",
    "Price":2.059,
    "Name":"NightOwl BP Clifton Beach",
    "Address":"55-57 Endeavour Road",
    "Postcode":"4879",
    "Fuel_Name":"Diesel"
  },
  {
    "Site_ID":61470573,
    "Fuel_ID":3,
    "TransactionDate":"2026-06-20T10:10:17+10:00",
    "Price":1.959,
    "Name":"BP Earlville",
    "Address":"395 Mulgrave Rd & Mccoombe Rd",
    "Postcode":"4870",
    "Fuel_Name":"Diesel"
  },
  {
    "Site_ID":61470699,
    "Fuel_ID":3,
    "TransactionDate":"2026-06-19T21:36:18+10:00",
    "Price":1.959,
    "Name":"BP Kuranda",
    "Address":"3 Rob Veivers Drive",
    "Postcode":"4881",
    "Fuel_Name":"Diesel"
  },
  {
    "Site_ID":61477011,
    "Fuel_ID":3,
    "TransactionDate":"2026-06-19T15:35:34+10:00",
    "Price":1.895,
    "Name":"Liberty Manoora",
    "Address":"31-35 Reservoir Rd",
    "Postcode":"4870",
    "Fuel_Name":"Diesel"
  },
  {
    "Site_ID":61477041,
    "Fuel_ID":3,
    "TransactionDate":"2026-06-19T18:40:23+10:00",
    "Price":1.889,
    "Name":"OOM Energy Cairns Central",
    "Address":"Cnr Martyn & Florence St",
    "Postcode":"4870",
    "Fuel_Name":"Diesel"
  },
  {
    "Site_ID":61477062,
    "Fuel_ID":3,
    "TransactionDate":"2026-06-20T10:10:17+10:00",
    "Price":1.959,
    "Name":"BP Smithfield Cairns",
    "Address":"Captain Cook Hwy",
    "Postcode":"4878",
    "Fuel_Name":"Diesel"
  },
  {
    "Site_ID":61477095,
    "Fuel_ID":3,
    "TransactionDate":"2026-06-19T10:30:30+10:00",
    "Price":1.959,
    "Name":"Shell Reddy Express Redlynch",
    "Address":"1A Chelsea Lane",
    "Postcode":"4878",
    "Fuel_Name":"Diesel"
  },
  {
    "Site_ID":61477106,
    "Fuel_ID":3,
    "TransactionDate":"2026-06-18T09:26:44+10:00",
    "Price":2.079,
    "Name":"Marano\u2019s Fuel Wonga",
    "Address":"3 Oleander Drive",
    "Postcode":"4873",
    "Fuel_Name":"Diesel"
  },
  {
    "Site_ID":61477674,
    "Fuel_ID":3,
    "TransactionDate":"2026-06-18T08:35:19+10:00",
    "Price":1.925,
    "Name":"Edge Hill Servo",
    "Address":"134 Collins Ave",
    "Postcode":"4870",
    "Fuel_Name":"Diesel"
  },
  {
    "Site_ID":61477719,
    "Fuel_ID":3,
    "TransactionDate":"2026-06-19T10:30:30+10:00",
    "Price":1.959,
    "Name":"Shell Reddy Express Cairns Mulgrave Rd",
    "Address":"87 Mulgrave Rd",
    "Postcode":"4870",
    "Fuel_Name":"Diesel"
  },
  {
    "Site_ID":61477726,
    "Fuel_ID":3,
    "TransactionDate":"2026-06-05T08:12:01+10:00",
    "Price":2.089,
    "Name":"White Rock General Store",
    "Address":"150 Progress Road",
    "Postcode":"4868",
    "Fuel_Name":"Diesel"
  },
  {
    "Site_ID":61477727,
    "Fuel_ID":3,
    "TransactionDate":"2026-06-18T09:07:24+10:00",
    "Price":1.925,
    "Name":"Machans Beach Store and Post Office",
    "Address":"27 Machans Street",
    "Postcode":"4878",
    "Fuel_Name":"Diesel"
  },
  {
    "Site_ID":61477771,
    "Fuel_ID":3,
    "TransactionDate":"2026-06-17T06:31:23+10:00",
    "Price":2.079,
    "Name":"Eacham Fuels",
    "Address":"8 Pioneer Avenue",
    "Postcode":"4885",
    "Fuel_Name":"Diesel"
  },
  {
    "Site_ID":61477804,
    "Fuel_ID":3,
    "TransactionDate":"2026-06-18T06:07:32+10:00",
    "Price":1.987,
    "Name":"Stratford Driveway Discount Fuels",
    "Address":"2-4 Rinks Close",
    "Postcode":"4870",
    "Fuel_Name":"Diesel"
  },
  {
    "Site_ID":61477805,
    "Fuel_ID":3,
    "TransactionDate":"2026-06-19T10:08:25+10:00",
    "Price":1.955,
    "Name":"Mobil Edmonton Central",
    "Address":"59-63 Hambleton Drive",
    "Postcode":"4869",
    "Fuel_Name":"Diesel"
  },
  {
    "Site_ID":61477814,
    "Fuel_ID":3,
    "TransactionDate":"2026-06-18T09:12:35+10:00",
    "Price":2.079,
    "Name":"Miallo Fuel Station",
    "Address":"735 Daintree Road",
    "Postcode":"4873",
    "Fuel_Name":"Diesel"
  },
  {
    "Site_ID":61477816,
    "Fuel_ID":3,
    "TransactionDate":"2026-06-18T10:17:14+10:00",
    "Price":2.079,
    "Name":"Roadhouse Service Station",
    "Address":"129 Alchera Drive",
    "Postcode":"4873",
    "Fuel_Name":"Diesel"
  },
  {
    "Site_ID":61477819,
    "Fuel_ID":3,
    "TransactionDate":"2026-06-18T09:17:35+10:00",
    "Price":2.079,
    "Name":"Port Douglas Service Station",
    "Address":" Port Street",
    "Postcode":"4871",
    "Fuel_Name":"Diesel"
  },
  {
    "Site_ID":61477822,
    "Fuel_ID":3,
    "TransactionDate":"2026-06-18T09:37:47+10:00",
    "Price":2.079,
    "Name":"Raintrees Cafe and Servo",
    "Address":"2 Foxton Avenue",
    "Postcode":"4873",
    "Fuel_Name":"Diesel"
  },
  {
    "Site_ID":61477837,
    "Fuel_ID":3,
    "TransactionDate":"2026-06-18T12:03:22+10:00",
    "Price":2.079,
    "Name":"BP Port Douglas",
    "Address":"5946 Davidson Street",
    "Postcode":"4877",
    "Fuel_Name":"Diesel"
  },
  {
    "Site_ID":61477839,
    "Fuel_ID":3,
    "TransactionDate":"2026-06-09T13:08:39+10:00",
    "Price":2.219,
    "Name":"Wondecla Service Station",
    "Address":"1190 Longlands Gap Rd",
    "Postcode":"4887",
    "Fuel_Name":"Diesel"
  },
  {
    "Site_ID":61477987,
    "Fuel_ID":3,
    "TransactionDate":"2026-06-20T08:15:39+10:00",
    "Price":1.895,
    "Name":"Mobil Sheridan Street",
    "Address":"237-241 Sheridan Street",
    "Postcode":"4870",
    "Fuel_Name":"Diesel"
  },
  {
    "Site_ID":61478023,
    "Fuel_ID":3,
    "TransactionDate":"2026-06-18T09:31:48+10:00",
    "Price":1.999,
    "Name":"Marano\u2019s Fuel Edmonton",
    "Address":"69-70 Thomson Road",
    "Postcode":"4869",
    "Fuel_Name":"Diesel"
  },
  {
    "Site_ID":61478243,
    "Fuel_ID":3,
    "TransactionDate":"2026-06-19T15:50:04+10:00",
    "Price":1.965,
    "Name":"NightOwl BP Anderson Street",
    "Address":"66-68 Anderson St",
    "Postcode":"4870",
    "Fuel_Name":"Diesel"
  },
  {
    "Site_ID":61478266,
    "Fuel_ID":3,
    "TransactionDate":"2026-06-19T16:31:42+10:00",
    "Price":1.899,
    "Name":"Woodham Petroleum Cairns",
    "Address":"104 Aumuller St",
    "Postcode":"4870",
    "Fuel_Name":"Diesel"
  },
  {
    "Site_ID":61470086,
    "Fuel_ID":4,
    "TransactionDate":"2026-06-02T06:46:38+10:00",
    "Price":1.549,
    "Name":"Mobil on Spence",
    "Address":"142A-146 Spence Street",
    "Postcode":"4870",
    "Fuel_Name":"LPG"
  },
  {
    "Site_ID":61401991,
    "Fuel_ID":5,
    "TransactionDate":"2026-06-18T18:54:54+10:00",
    "Price":1.825,
    "Name":"BP Edmonton",
    "Address":"3\/167 Bruce Hwy",
    "Postcode":"4869",
    "Fuel_Name":"Premium Unleaded 95"
  },
  {
    "Site_ID":61402009,
    "Fuel_ID":5,
    "TransactionDate":"2026-06-18T09:07:33+10:00",
    "Price":1.869,
    "Name":"Ampol Mossman",
    "Address":"67 Alchera",
    "Postcode":"4873",
    "Fuel_Name":"Premium Unleaded 95"
  },
  {
    "Site_ID":61402015,
    "Fuel_ID":5,
    "TransactionDate":"2026-06-18T10:37:29+10:00",
    "Price":1.829,
    "Name":"Billabong Service Centre",
    "Address":"Captain Cook Hwy",
    "Postcode":"4879",
    "Fuel_Name":"Premium Unleaded 95"
  },
  {
    "Site_ID":61402067,
    "Fuel_ID":5,
    "TransactionDate":"2026-06-19T16:05:52+10:00",
    "Price":1.815,
    "Name":"Caltex Woree",
    "Address":"590 Mulgrave Rd",
    "Postcode":"4868",
    "Fuel_Name":"Premium Unleaded 95"
  },
  {
    "Site_ID":61402073,
    "Fuel_ID":5,
    "TransactionDate":"2026-06-19T15:32:17+10:00",
    "Price":1.819,
    "Name":"Ampol Foodary Cairns Sheridan St",
    "Address":"131 Sheridan St",
    "Postcode":"4870",
    "Fuel_Name":"Premium Unleaded 95"
  },
  {
    "Site_ID":61402272,
    "Fuel_ID":5,
    "TransactionDate":"2026-06-20T09:02:41+10:00",
    "Price":1.775,
    "Name":"Mobil Brinsmead",
    "Address":"101-115 Brinsmead Road",
    "Postcode":"4870",
    "Fuel_Name":"Premium Unleaded 95"
  },
  {
    "Site_ID":61402555,
    "Fuel_ID":5,
    "TransactionDate":"2026-06-18T09:14:05+10:00",
    "Price":1.899,
    "Name":"Astron Twin Rivers",
    "Address":"68929 Bruce Highway",
    "Postcode":"4871",
    "Fuel_Name":"Premium Unleaded 95"
  },
  {
    "Site_ID":61402769,
    "Fuel_ID":5,
    "TransactionDate":"2026-06-17T10:00:10+10:00",
    "Price":1.835,
    "Name":"United Koah",
    "Address":"2 Koah Rd",
    "Postcode":"4872",
    "Fuel_Name":"Premium Unleaded 95"
  },
  {
    "Site_ID":61402795,
    "Fuel_ID":5,
    "TransactionDate":"2026-06-18T10:25:09+10:00",
    "Price":1.809,
    "Name":"BP Mossman",
    "Address":"68 Pringle St",
    "Postcode":"4873",
    "Fuel_Name":"Premium Unleaded 95"
  },
  {
    "Site_ID":61402827,
    "Fuel_ID":5,
    "TransactionDate":"2026-06-19T16:05:07+10:00",
    "Price":1.775,
    "Name":"United Cairns North",
    "Address":"238 Sheridan Street",
    "Postcode":"4870",
    "Fuel_Name":"Premium Unleaded 95"
  },
  {
    "Site_ID":61402828,
    "Fuel_ID":5,
    "TransactionDate":"2026-06-10T10:20:08+10:00",
    "Price":1.755,
    "Name":"United Woree",
    "Address":"6 Southgate Close",
    "Postcode":"4868",
    "Fuel_Name":"Premium Unleaded 95"
  },
  {
    "Site_ID":61451561,
    "Fuel_ID":5,
    "TransactionDate":"2026-06-20T08:38:42+10:00",
    "Price":1.775,
    "Name":"Mobil Edmonton",
    "Address":"75 Bruce Hwy",
    "Postcode":"4869",
    "Fuel_Name":"Premium Unleaded 95"
  },
  {
    "Site_ID":61451567,
    "Fuel_ID":5,
    "TransactionDate":"2026-06-19T10:30:30+10:00",
    "Price":1.834,
    "Name":"Shell Reddy Express Cairns Sheridan St",
    "Address":"291-293 Sheridan St",
    "Postcode":"4870",
    "Fuel_Name":"Premium Unleaded 95"
  },
  {
    "Site_ID":61451572,
    "Fuel_ID":5,
    "TransactionDate":"2026-06-17T09:30:34+10:00",
    "Price":1.854,
    "Name":"Shell Reddy Express Smithfield (Qld)",
    "Address":"Lot 1 Captain Cook Hwy",
    "Postcode":"4878",
    "Fuel_Name":"Premium Unleaded 95"
  },
  {
    "Site_ID":61451722,
    "Fuel_ID":5,
    "TransactionDate":"2026-06-18T08:07:49+10:00",
    "Price":1.795,
    "Name":"Mobil Yorkey's Knob",
    "Address":"233 Yorkeys Knob Road",
    "Postcode":"4878",
    "Fuel_Name":"Premium Unleaded 95"
  },
  {
    "Site_ID":61451728,
    "Fuel_ID":5,
    "TransactionDate":"2026-06-18T09:26:41+10:00",
    "Price":1.829,
    "Name":"Shell Cairns",
    "Address":"8 Kenny St, Portsmith QLD 4870, Australia",
    "Postcode":"4870",
    "Fuel_Name":"Premium Unleaded 95"
  },
  {
    "Site_ID":61451734,
    "Fuel_ID":5,
    "TransactionDate":"2026-06-19T10:35:24+10:00",
    "Price":1.894,
    "Name":"Shell Reddy Express Port Douglas",
    "Address":"10 Captain Cook Hwy",
    "Postcode":"4877",
    "Fuel_Name":"Premium Unleaded 95"
  },
  {
    "Site_ID":61470034,
    "Fuel_ID":5,
    "TransactionDate":"2026-06-06T07:32:42+10:00",
    "Price":1.795,
    "Name":"Mobil Gordonvale",
    "Address":"67 George St",
    "Postcode":"4865",
    "Fuel_Name":"Premium Unleaded 95"
  },
  {
    "Site_ID":61470115,
    "Fuel_ID":5,
    "TransactionDate":"2026-06-09T13:08:39+10:00",
    "Price":1.979,
    "Name":"Thorpe Earthmoving",
    "Address":"14 Perkins Street",
    "Postcode":"4887",
    "Fuel_Name":"Premium Unleaded 95"
  },
  {
    "Site_ID":61470145,
    "Fuel_ID":5,
    "TransactionDate":"2026-06-19T06:14:32+10:00",
    "Price":1.879,
    "Name":"Ampol Port Douglas",
    "Address":"13 Warner St",
    "Postcode":"4871",
    "Fuel_Name":"Premium Unleaded 95"
  },
  {
    "Site_ID":61470301,
    "Fuel_ID":5,
    "TransactionDate":"2026-06-16T07:55:03+10:00",
    "Price":1.839,
    "Name":"NightOwl BP Clifton Beach",
    "Address":"55-57 Endeavour Road",
    "Postcode":"4879",
    "Fuel_Name":"Premium Unleaded 95"
  },
  {
    "Site_ID":61470573,
    "Fuel_ID":5,
    "TransactionDate":"2026-06-20T10:10:17+10:00",
    "Price":1.829,
    "Name":"BP Earlville",
    "Address":"395 Mulgrave Rd & Mccoombe Rd",
    "Postcode":"4870",
    "Fuel_Name":"Premium Unleaded 95"
  },
  {
    "Site_ID":61477041,
    "Fuel_ID":5,
    "TransactionDate":"2026-06-19T18:40:23+10:00",
    "Price":1.745,
    "Name":"OOM Energy Cairns Central",
    "Address":"Cnr Martyn & Florence St",
    "Postcode":"4870",
    "Fuel_Name":"Premium Unleaded 95"
  },
  {
    "Site_ID":61477062,
    "Fuel_ID":5,
    "TransactionDate":"2026-06-20T10:10:17+10:00",
    "Price":1.869,
    "Name":"BP Smithfield Cairns",
    "Address":"Captain Cook Hwy",
    "Postcode":"4878",
    "Fuel_Name":"Premium Unleaded 95"
  },
  {
    "Site_ID":61477106,
    "Fuel_ID":5,
    "TransactionDate":"2026-06-18T09:26:50+10:00",
    "Price":1.869,
    "Name":"Marano\u2019s Fuel Wonga",
    "Address":"3 Oleander Drive",
    "Postcode":"4873",
    "Fuel_Name":"Premium Unleaded 95"
  },
  {
    "Site_ID":61477674,
    "Fuel_ID":5,
    "TransactionDate":"2026-06-18T08:35:19+10:00",
    "Price":1.805,
    "Name":"Edge Hill Servo",
    "Address":"134 Collins Ave",
    "Postcode":"4870",
    "Fuel_Name":"Premium Unleaded 95"
  },
  {
    "Site_ID":61477719,
    "Fuel_ID":5,
    "TransactionDate":"2026-06-19T10:30:30+10:00",
    "Price":1.824,
    "Name":"Shell Reddy Express Cairns Mulgrave Rd",
    "Address":"87 Mulgrave Rd",
    "Postcode":"4870",
    "Fuel_Name":"Premium Unleaded 95"
  },
  {
    "Site_ID":61477726,
    "Fuel_ID":5,
    "TransactionDate":"2026-06-04T07:04:38+10:00",
    "Price":1.899,
    "Name":"White Rock General Store",
    "Address":"150 Progress Road",
    "Postcode":"4868",
    "Fuel_Name":"Premium Unleaded 95"
  },
  {
    "Site_ID":61477727,
    "Fuel_ID":5,
    "TransactionDate":"2026-06-18T09:07:24+10:00",
    "Price":1.805,
    "Name":"Machans Beach Store and Post Office",
    "Address":"27 Machans Street",
    "Postcode":"4878",
    "Fuel_Name":"Premium Unleaded 95"
  },
  {
    "Site_ID":61477771,
    "Fuel_ID":5,
    "TransactionDate":"2026-06-15T06:50:13+10:00",
    "Price":1.899,
    "Name":"Eacham Fuels",
    "Address":"8 Pioneer Avenue",
    "Postcode":"4885",
    "Fuel_Name":"Premium Unleaded 95"
  },
  {
    "Site_ID":61477804,
    "Fuel_ID":5,
    "TransactionDate":"2026-06-10T17:44:48+10:00",
    "Price":1.917,
    "Name":"Stratford Driveway Discount Fuels",
    "Address":"2-4 Rinks Close",
    "Postcode":"4870",
    "Fuel_Name":"Premium Unleaded 95"
  },
  {
    "Site_ID":61477805,
    "Fuel_ID":5,
    "TransactionDate":"2026-06-19T10:08:25+10:00",
    "Price":1.795,
    "Name":"Mobil Edmonton Central",
    "Address":"59-63 Hambleton Drive",
    "Postcode":"4869",
    "Fuel_Name":"Premium Unleaded 95"
  },
  {
    "Site_ID":61477814,
    "Fuel_ID":5,
    "TransactionDate":"2026-06-18T09:12:35+10:00",
    "Price":1.869,
    "Name":"Miallo Fuel Station",
    "Address":"735 Daintree Road",
    "Postcode":"4873",
    "Fuel_Name":"Premium Unleaded 95"
  },
  {
    "Site_ID":61477816,
    "Fuel_ID":5,
    "TransactionDate":"2026-06-18T10:17:15+10:00",
    "Price":1.869,
    "Name":"Roadhouse Service Station",
    "Address":"129 Alchera Drive",
    "Postcode":"4873",
    "Fuel_Name":"Premium Unleaded 95"
  },
  {
    "Site_ID":61477819,
    "Fuel_ID":5,
    "TransactionDate":"2026-06-18T09:17:35+10:00",
    "Price":1.869,
    "Name":"Port Douglas Service Station",
    "Address":" Port Street",
    "Postcode":"4871",
    "Fuel_Name":"Premium Unleaded 95"
  },
  {
    "Site_ID":61477822,
    "Fuel_ID":5,
    "TransactionDate":"2026-06-18T09:37:47+10:00",
    "Price":1.869,
    "Name":"Raintrees Cafe and Servo",
    "Address":"2 Foxton Avenue",
    "Postcode":"4873",
    "Fuel_Name":"Premium Unleaded 95"
  },
  {
    "Site_ID":61477839,
    "Fuel_ID":5,
    "TransactionDate":"2026-06-09T13:08:39+10:00",
    "Price":1.979,
    "Name":"Wondecla Service Station",
    "Address":"1190 Longlands Gap Rd",
    "Postcode":"4887",
    "Fuel_Name":"Premium Unleaded 95"
  },
  {
    "Site_ID":61477987,
    "Fuel_ID":5,
    "TransactionDate":"2026-06-20T08:15:39+10:00",
    "Price":1.745,
    "Name":"Mobil Sheridan Street",
    "Address":"237-241 Sheridan Street",
    "Postcode":"4870",
    "Fuel_Name":"Premium Unleaded 95"
  },
  {
    "Site_ID":61478023,
    "Fuel_ID":5,
    "TransactionDate":"2026-06-18T09:31:48+10:00",
    "Price":1.829,
    "Name":"Marano\u2019s Fuel Edmonton",
    "Address":"69-70 Thomson Road",
    "Postcode":"4869",
    "Fuel_Name":"Premium Unleaded 95"
  },
  {
    "Site_ID":61478243,
    "Fuel_ID":5,
    "TransactionDate":"2026-06-18T14:25:05+10:00",
    "Price":1.829,
    "Name":"NightOwl BP Anderson Street",
    "Address":"66-68 Anderson St",
    "Postcode":"4870",
    "Fuel_Name":"Premium Unleaded 95"
  },
  {
    "Site_ID":61401973,
    "Fuel_ID":8,
    "TransactionDate":"2026-06-20T09:05:07+10:00",
    "Price":1.915,
    "Name":"United Gordonvale",
    "Address":"68 Riverstone Road",
    "Postcode":"4865",
    "Fuel_Name":"Premium Unleaded 98"
  },
  {
    "Site_ID":61402015,
    "Fuel_ID":8,
    "TransactionDate":"2026-06-18T10:37:30+10:00",
    "Price":1.989,
    "Name":"Billabong Service Centre",
    "Address":"Captain Cook Hwy",
    "Postcode":"4879",
    "Fuel_Name":"Premium Unleaded 98"
  },
  {
    "Site_ID":61402067,
    "Fuel_ID":8,
    "TransactionDate":"2026-06-19T16:05:52+10:00",
    "Price":1.915,
    "Name":"Caltex Woree",
    "Address":"590 Mulgrave Rd",
    "Postcode":"4868",
    "Fuel_Name":"Premium Unleaded 98"
  },
  {
    "Site_ID":61402393,
    "Fuel_ID":8,
    "TransactionDate":"2026-06-19T09:28:43+10:00",
    "Price":1.949,
    "Name":"Caltex Stratford",
    "Address":"45 Arnold St",
    "Postcode":"4870",
    "Fuel_Name":"Premium Unleaded 98"
  },
  {
    "Site_ID":61402394,
    "Fuel_ID":8,
    "TransactionDate":"2026-06-18T12:19:17+10:00",
    "Price":1.949,
    "Name":"Caltex Bentley Park",
    "Address":"28 Supply Rd",
    "Postcode":"4869",
    "Fuel_Name":"Premium Unleaded 98"
  },
  {
    "Site_ID":61402395,
    "Fuel_ID":8,
    "TransactionDate":"2026-06-15T11:10:02+10:00",
    "Price":1.949,
    "Name":"Caltex Portsmith",
    "Address":"104 Cook St, Portsmith QLD 4870, Australia",
    "Postcode":"4870",
    "Fuel_Name":"Premium Unleaded 98"
  },
  {
    "Site_ID":61402827,
    "Fuel_ID":8,
    "TransactionDate":"2026-06-19T16:05:07+10:00",
    "Price":1.865,
    "Name":"United Cairns North",
    "Address":"238 Sheridan Street",
    "Postcode":"4870",
    "Fuel_Name":"Premium Unleaded 98"
  },
  {
    "Site_ID":61402828,
    "Fuel_ID":8,
    "TransactionDate":"2026-06-10T10:20:08+10:00",
    "Price":1.845,
    "Name":"United Woree",
    "Address":"6 Southgate Close",
    "Postcode":"4868",
    "Fuel_Name":"Premium Unleaded 98"
  },
  {
    "Site_ID":61402869,
    "Fuel_ID":8,
    "TransactionDate":"2026-06-20T09:15:07+10:00",
    "Price":1.915,
    "Name":"United Gordonvale Cairns Road",
    "Address":"105-115 Cairns Road",
    "Postcode":"4865",
    "Fuel_Name":"Premium Unleaded 98"
  },
  {
    "Site_ID":61451566,
    "Fuel_ID":8,
    "TransactionDate":"2026-06-19T10:45:25+10:00",
    "Price":1.949,
    "Name":"Shell Reddy Express Reservoir (Qld)",
    "Address":"58 Pease St",
    "Postcode":"4870",
    "Fuel_Name":"Premium Unleaded 98"
  },
  {
    "Site_ID":61451567,
    "Fuel_ID":8,
    "TransactionDate":"2026-06-19T10:30:30+10:00",
    "Price":1.929,
    "Name":"Shell Reddy Express Cairns Sheridan St",
    "Address":"291-293 Sheridan St",
    "Postcode":"4870",
    "Fuel_Name":"Premium Unleaded 98"
  },
  {
    "Site_ID":61451572,
    "Fuel_ID":8,
    "TransactionDate":"2026-06-17T09:30:34+10:00",
    "Price":1.949,
    "Name":"Shell Reddy Express Smithfield (Qld)",
    "Address":"Lot 1 Captain Cook Hwy",
    "Postcode":"4878",
    "Fuel_Name":"Premium Unleaded 98"
  },
  {
    "Site_ID":61451666,
    "Fuel_ID":8,
    "TransactionDate":"2026-06-19T15:30:34+10:00",
    "Price":1.845,
    "Name":"Liberty Woree",
    "Address":"540 Mulgrave Road",
    "Postcode":"4868",
    "Fuel_Name":"Premium Unleaded 98"
  },
  {
    "Site_ID":61451728,
    "Fuel_ID":8,
    "TransactionDate":"2026-06-18T09:26:42+10:00",
    "Price":1.989,
    "Name":"Shell Cairns",
    "Address":"8 Kenny St, Portsmith QLD 4870, Australia",
    "Postcode":"4870",
    "Fuel_Name":"Premium Unleaded 98"
  },
  {
    "Site_ID":61451734,
    "Fuel_ID":8,
    "TransactionDate":"2026-06-19T10:35:24+10:00",
    "Price":1.989,
    "Name":"Shell Reddy Express Port Douglas",
    "Address":"10 Captain Cook Hwy",
    "Postcode":"4877",
    "Fuel_Name":"Premium Unleaded 98"
  },
  {
    "Site_ID":61470086,
    "Fuel_ID":8,
    "TransactionDate":"2026-06-04T12:55:53+10:00",
    "Price":1.895,
    "Name":"Mobil on Spence",
    "Address":"142A-146 Spence Street",
    "Postcode":"4870",
    "Fuel_Name":"Premium Unleaded 98"
  },
  {
    "Site_ID":61470301,
    "Fuel_ID":8,
    "TransactionDate":"2026-06-10T12:05:07+10:00",
    "Price":1.999,
    "Name":"NightOwl BP Clifton Beach",
    "Address":"55-57 Endeavour Road",
    "Postcode":"4879",
    "Fuel_Name":"Premium Unleaded 98"
  },
  {
    "Site_ID":61470573,
    "Fuel_ID":8,
    "TransactionDate":"2026-06-20T10:10:17+10:00",
    "Price":1.919,
    "Name":"BP Earlville",
    "Address":"395 Mulgrave Rd & Mccoombe Rd",
    "Postcode":"4870",
    "Fuel_Name":"Premium Unleaded 98"
  },
  {
    "Site_ID":61470699,
    "Fuel_ID":8,
    "TransactionDate":"2026-06-19T10:18:04+10:00",
    "Price":1.949,
    "Name":"BP Kuranda",
    "Address":"3 Rob Veivers Drive",
    "Postcode":"4881",
    "Fuel_Name":"Premium Unleaded 98"
  },
  {
    "Site_ID":61477011,
    "Fuel_ID":8,
    "TransactionDate":"2026-06-19T15:35:32+10:00",
    "Price":1.865,
    "Name":"Liberty Manoora",
    "Address":"31-35 Reservoir Rd",
    "Postcode":"4870",
    "Fuel_Name":"Premium Unleaded 98"
  },
  {
    "Site_ID":61477020,
    "Fuel_ID":8,
    "TransactionDate":"2026-06-19T15:32:17+10:00",
    "Price":1.919,
    "Name":"Ampol Foodary Manunda",
    "Address":"1 Hoare St & Gatton Rd",
    "Postcode":"4870",
    "Fuel_Name":"Premium Unleaded 98"
  },
  {
    "Site_ID":61477062,
    "Fuel_ID":8,
    "TransactionDate":"2026-06-20T10:10:17+10:00",
    "Price":1.959,
    "Name":"BP Smithfield Cairns",
    "Address":"Captain Cook Hwy",
    "Postcode":"4878",
    "Fuel_Name":"Premium Unleaded 98"
  },
  {
    "Site_ID":61477095,
    "Fuel_ID":8,
    "TransactionDate":"2026-06-17T09:35:23+10:00",
    "Price":1.969,
    "Name":"Shell Reddy Express Redlynch",
    "Address":"1A Chelsea Lane",
    "Postcode":"4878",
    "Fuel_Name":"Premium Unleaded 98"
  },
  {
    "Site_ID":61477719,
    "Fuel_ID":8,
    "TransactionDate":"2026-06-19T10:30:30+10:00",
    "Price":1.919,
    "Name":"Shell Reddy Express Cairns Mulgrave Rd",
    "Address":"87 Mulgrave Rd",
    "Postcode":"4870",
    "Fuel_Name":"Premium Unleaded 98"
  },
  {
    "Site_ID":61477805,
    "Fuel_ID":8,
    "TransactionDate":"2026-06-19T10:08:25+10:00",
    "Price":1.895,
    "Name":"Mobil Edmonton Central",
    "Address":"59-63 Hambleton Drive",
    "Postcode":"4869",
    "Fuel_Name":"Premium Unleaded 98"
  },
  {
    "Site_ID":61477837,
    "Fuel_ID":8,
    "TransactionDate":"2026-06-18T12:03:22+10:00",
    "Price":2.009,
    "Name":"BP Port Douglas",
    "Address":"5946 Davidson Street",
    "Postcode":"4877",
    "Fuel_Name":"Premium Unleaded 98"
  },
  {
    "Site_ID":61477987,
    "Fuel_ID":8,
    "TransactionDate":"2026-06-20T08:15:39+10:00",
    "Price":1.845,
    "Name":"Mobil Sheridan Street",
    "Address":"237-241 Sheridan Street",
    "Postcode":"4870",
    "Fuel_Name":"Premium Unleaded 98"
  },
  {
    "Site_ID":61478023,
    "Fuel_ID":8,
    "TransactionDate":"2026-06-18T09:31:49+10:00",
    "Price":1.989,
    "Name":"Marano\u2019s Fuel Edmonton",
    "Address":"69-70 Thomson Road",
    "Postcode":"4869",
    "Fuel_Name":"Premium Unleaded 98"
  },
  {
    "Site_ID":61478243,
    "Fuel_ID":8,
    "TransactionDate":"2026-06-18T14:25:05+10:00",
    "Price":1.999,
    "Name":"NightOwl BP Anderson Street",
    "Address":"66-68 Anderson St",
    "Postcode":"4870",
    "Fuel_Name":"Premium Unleaded 98"
  },
  {
    "Site_ID":61402073,
    "Fuel_ID":12,
    "TransactionDate":"2026-06-19T15:32:17+10:00",
    "Price":1.649,
    "Name":"Ampol Foodary Cairns Sheridan St",
    "Address":"131 Sheridan St",
    "Postcode":"4870",
    "Fuel_Name":"e10"
  },
  {
    "Site_ID":61402272,
    "Fuel_ID":12,
    "TransactionDate":"2026-06-20T09:02:41+10:00",
    "Price":1.655,
    "Name":"Mobil Brinsmead",
    "Address":"101-115 Brinsmead Road",
    "Postcode":"4870",
    "Fuel_Name":"e10"
  },
  {
    "Site_ID":61402393,
    "Fuel_ID":12,
    "TransactionDate":"2026-06-19T09:28:43+10:00",
    "Price":1.679,
    "Name":"Caltex Stratford",
    "Address":"45 Arnold St",
    "Postcode":"4870",
    "Fuel_Name":"e10"
  },
  {
    "Site_ID":61402394,
    "Fuel_ID":12,
    "TransactionDate":"2026-06-18T12:19:17+10:00",
    "Price":1.679,
    "Name":"Caltex Bentley Park",
    "Address":"28 Supply Rd",
    "Postcode":"4869",
    "Fuel_Name":"e10"
  },
  {
    "Site_ID":61402395,
    "Fuel_ID":12,
    "TransactionDate":"2026-06-15T11:10:02+10:00",
    "Price":1.679,
    "Name":"Caltex Portsmith",
    "Address":"104 Cook St, Portsmith QLD 4870, Australia",
    "Postcode":"4870",
    "Fuel_Name":"e10"
  },
  {
    "Site_ID":61402555,
    "Fuel_ID":12,
    "TransactionDate":"2026-06-18T09:14:05+10:00",
    "Price":1.789,
    "Name":"Astron Twin Rivers",
    "Address":"68929 Bruce Highway",
    "Postcode":"4871",
    "Fuel_Name":"e10"
  },
  {
    "Site_ID":61402769,
    "Fuel_ID":12,
    "TransactionDate":"2026-06-17T10:00:10+10:00",
    "Price":1.675,
    "Name":"United Koah",
    "Address":"2 Koah Rd",
    "Postcode":"4872",
    "Fuel_Name":"e10"
  },
  {
    "Site_ID":61402827,
    "Fuel_ID":12,
    "TransactionDate":"2026-06-19T16:05:07+10:00",
    "Price":1.615,
    "Name":"United Cairns North",
    "Address":"238 Sheridan Street",
    "Postcode":"4870",
    "Fuel_Name":"e10"
  },
  {
    "Site_ID":61402828,
    "Fuel_ID":12,
    "TransactionDate":"2026-06-10T10:20:08+10:00",
    "Price":1.595,
    "Name":"United Woree",
    "Address":"6 Southgate Close",
    "Postcode":"4868",
    "Fuel_Name":"e10"
  },
  {
    "Site_ID":61402869,
    "Fuel_ID":12,
    "TransactionDate":"2026-06-20T09:15:07+10:00",
    "Price":1.655,
    "Name":"United Gordonvale Cairns Road",
    "Address":"105-115 Cairns Road",
    "Postcode":"4865",
    "Fuel_Name":"e10"
  },
  {
    "Site_ID":61402891,
    "Fuel_ID":12,
    "TransactionDate":"2026-06-11T16:30:34+10:00",
    "Price":1.679,
    "Name":"Shell Reddy Express Edmonton",
    "Address":"9-11 Walker Rd (Cnr Hambledon Dr)",
    "Postcode":"4869",
    "Fuel_Name":"e10"
  },
  {
    "Site_ID":61451567,
    "Fuel_ID":12,
    "TransactionDate":"2026-06-19T10:30:30+10:00",
    "Price":1.639,
    "Name":"Shell Reddy Express Cairns Sheridan St",
    "Address":"291-293 Sheridan St",
    "Postcode":"4870",
    "Fuel_Name":"e10"
  },
  {
    "Site_ID":61451572,
    "Fuel_ID":12,
    "TransactionDate":"2026-06-17T09:30:34+10:00",
    "Price":1.679,
    "Name":"Shell Reddy Express Smithfield (Qld)",
    "Address":"Lot 1 Captain Cook Hwy",
    "Postcode":"4878",
    "Fuel_Name":"e10"
  },
  {
    "Site_ID":61451666,
    "Fuel_ID":12,
    "TransactionDate":"2026-06-19T15:30:36+10:00",
    "Price":1.575,
    "Name":"Liberty Woree",
    "Address":"540 Mulgrave Road",
    "Postcode":"4868",
    "Fuel_Name":"e10"
  },
  {
    "Site_ID":61451722,
    "Fuel_ID":12,
    "TransactionDate":"2026-06-18T08:07:49+10:00",
    "Price":1.675,
    "Name":"Mobil Yorkey's Knob",
    "Address":"233 Yorkeys Knob Road",
    "Postcode":"4878",
    "Fuel_Name":"e10"
  },
  {
    "Site_ID":61470086,
    "Fuel_ID":12,
    "TransactionDate":"2026-06-04T12:55:53+10:00",
    "Price":1.675,
    "Name":"Mobil on Spence",
    "Address":"142A-146 Spence Street",
    "Postcode":"4870",
    "Fuel_Name":"e10"
  },
  {
    "Site_ID":61477011,
    "Fuel_ID":12,
    "TransactionDate":"2026-06-19T15:35:33+10:00",
    "Price":1.595,
    "Name":"Liberty Manoora",
    "Address":"31-35 Reservoir Rd",
    "Postcode":"4870",
    "Fuel_Name":"e10"
  },
  {
    "Site_ID":61477095,
    "Fuel_ID":12,
    "TransactionDate":"2026-06-17T09:35:23+10:00",
    "Price":1.679,
    "Name":"Shell Reddy Express Redlynch",
    "Address":"1A Chelsea Lane",
    "Postcode":"4878",
    "Fuel_Name":"e10"
  },
  {
    "Site_ID":61477719,
    "Fuel_ID":12,
    "TransactionDate":"2026-06-19T10:30:30+10:00",
    "Price":1.629,
    "Name":"Shell Reddy Express Cairns Mulgrave Rd",
    "Address":"87 Mulgrave Rd",
    "Postcode":"4870",
    "Fuel_Name":"e10"
  },
  {
    "Site_ID":61477805,
    "Fuel_ID":12,
    "TransactionDate":"2026-06-19T10:08:25+10:00",
    "Price":1.675,
    "Name":"Mobil Edmonton Central",
    "Address":"59-63 Hambleton Drive",
    "Postcode":"4869",
    "Fuel_Name":"e10"
  },
  {
    "Site_ID":61477987,
    "Fuel_ID":12,
    "TransactionDate":"2026-06-20T08:15:39+10:00",
    "Price":1.625,
    "Name":"Mobil Sheridan Street",
    "Address":"237-241 Sheridan Street",
    "Postcode":"4870",
    "Fuel_Name":"e10"
  },
  {
    "Site_ID":61402015,
    "Fuel_ID":14,
    "TransactionDate":"2026-06-18T10:37:30+10:00",
    "Price":2.109,
    "Name":"Billabong Service Centre",
    "Address":"Captain Cook Hwy",
    "Postcode":"4879",
    "Fuel_Name":"Premium Diesel"
  },
  {
    "Site_ID":61402067,
    "Fuel_ID":14,
    "TransactionDate":"2026-06-19T16:05:52+10:00",
    "Price":1.925,
    "Name":"Caltex Woree",
    "Address":"590 Mulgrave Rd",
    "Postcode":"4868",
    "Fuel_Name":"Premium Diesel"
  },
  {
    "Site_ID":61402073,
    "Fuel_ID":14,
    "TransactionDate":"2026-06-19T15:37:17+10:00",
    "Price":1.959,
    "Name":"Ampol Foodary Cairns Sheridan St",
    "Address":"131 Sheridan St",
    "Postcode":"4870",
    "Fuel_Name":"Premium Diesel"
  },
  {
    "Site_ID":61402357,
    "Fuel_ID":14,
    "TransactionDate":"2026-06-19T17:05:52+10:00",
    "Price":1.919,
    "Name":"Ampol Cairns",
    "Address":"60 Draper Street",
    "Postcode":"4870",
    "Fuel_Name":"Premium Diesel"
  },
  {
    "Site_ID":61402393,
    "Fuel_ID":14,
    "TransactionDate":"2026-06-19T14:27:53+10:00",
    "Price":1.999,
    "Name":"Caltex Stratford",
    "Address":"45 Arnold St",
    "Postcode":"4870",
    "Fuel_Name":"Premium Diesel"
  },
  {
    "Site_ID":61402394,
    "Fuel_ID":14,
    "TransactionDate":"2026-06-18T12:19:17+10:00",
    "Price":1.999,
    "Name":"Caltex Bentley Park",
    "Address":"28 Supply Rd",
    "Postcode":"4869",
    "Fuel_Name":"Premium Diesel"
  },
  {
    "Site_ID":61402395,
    "Fuel_ID":14,
    "TransactionDate":"2026-06-19T11:36:42+10:00",
    "Price":1.929,
    "Name":"Caltex Portsmith",
    "Address":"104 Cook St, Portsmith QLD 4870, Australia",
    "Postcode":"4870",
    "Fuel_Name":"Premium Diesel"
  },
  {
    "Site_ID":61451666,
    "Fuel_ID":14,
    "TransactionDate":"2026-06-19T15:30:40+10:00",
    "Price":1.925,
    "Name":"Liberty Woree",
    "Address":"540 Mulgrave Road",
    "Postcode":"4868",
    "Fuel_Name":"Premium Diesel"
  },
  {
    "Site_ID":61477011,
    "Fuel_ID":14,
    "TransactionDate":"2026-06-19T15:35:35+10:00",
    "Price":1.925,
    "Name":"Liberty Manoora",
    "Address":"31-35 Reservoir Rd",
    "Postcode":"4870",
    "Fuel_Name":"Premium Diesel"
  },
  {
    "Site_ID":61477020,
    "Fuel_ID":14,
    "TransactionDate":"2026-06-19T15:37:17+10:00",
    "Price":1.959,
    "Name":"Ampol Foodary Manunda",
    "Address":"1 Hoare St & Gatton Rd",
    "Postcode":"4870",
    "Fuel_Name":"Premium Diesel"
  },
  {
    "Site_ID":61477837,
    "Fuel_ID":14,
    "TransactionDate":"2026-06-18T12:03:22+10:00",
    "Price":2.139,
    "Name":"BP Port Douglas",
    "Address":"5946 Davidson Street",
    "Postcode":"4877",
    "Fuel_Name":"Premium Diesel"
  },
  {
    "Site_ID":61478243,
    "Fuel_ID":14,
    "TransactionDate":"2026-06-19T15:50:04+10:00",
    "Price":1.98,
    "Name":"NightOwl BP Anderson Street",
    "Address":"66-68 Anderson St",
    "Postcode":"4870",
    "Fuel_Name":"Premium Diesel"
  }
]